sandboxed_python/__init__.py
sandboxed_python/finite_python.py
sandboxed_python/tests/test_core.py
sandboxed_python-0.1.0.dist-info/METADATA
sandboxed_python-0.1.0.dist-info/WHEEL
sandboxed_python-0.1.0.dist-info/entry_points.txt
sandboxed_python-0.1.0.dist-info/licenses/LICENSE
sandboxed_python-0.1.0.dist-info/RECORD
