Metadata-Version: 2.4
Name: sandboxed-python
Version: 0.1.0
Summary: Add your description here
Author-email: thautwarm <twshere@outlook.com>
License-File: LICENSE
Requires-Python: >=3.12
